deptrace/__init__.py
deptrace/__main__.py
deptrace/cli/__init__.py
deptrace/cli/actions.py
deptrace/cli/parse_args.py
deptrace/cli/run_analysis.py
deptrace/cli/functions/__init__.py
deptrace/cli/functions/analyze_file.py
deptrace/cli/functions/handle_output.py
deptrace/formatters/__init__.py
deptrace/formatters/write_graph_output.py
deptrace/formatters/functions/__init__.py
deptrace/formatters/functions/analyze_and_format_file.py
deptrace/import_crawler/build_graph.py
deptrace/import_crawler/crawl.py
deptrace/import_crawler/file_dependency_graph.py
deptrace/import_crawler/file_info.py
deptrace/import_crawler/find_local_module.py
deptrace/import_crawler/find_module.py
deptrace/import_crawler/find_module_in_syspath.py
deptrace/import_crawler/import_categorizer.py
deptrace/import_crawler/is_local_module.py
deptrace/import_crawler/is_source_layout_package.py
deptrace/import_crawler/package_finder.py
deptrace/import_crawler/package_searcher.py
deptrace/import_crawler/parse_file.py
deptrace/import_crawler/process_imports.py
deptrace/import_crawler/resolve_import.py
deptrace/import_crawler/site_packages.py
deptrace/logging/__init__.py
deptrace/logging/functions/configure_logging.py
deptrace/logging/functions/get_logger.py
deptrace/processors/__init__.py
deptrace/processors/process_file.py
deptrace/processors/process_scope.py
deptrace/processors/data/__init__.py
deptrace/processors/data/file_analysis.py
deptrace/processors/functions/__init__.py
deptrace/processors/functions/analyze_file.py
deptrace/processors/functions/format_analysis.py
deptrace/tools/__init__.py
deptrace/tools/convert_to_abs_path.py
deptrace/tools/parse_file.py
deptrace/visitors/__init__.py
deptrace/visitors/assignment_visitor.py
deptrace/visitors/scope_visitor.py
deptrace/visitors/call_tree/__init__.py
deptrace/visitors/call_tree/data/__init__.py
deptrace/visitors/call_tree/functions/__init__.py
deptrace/visitors/call_tree/functions/analyze_call_tree.py
deptrace-0.1.0.dist-info/METADATA
deptrace-0.1.0.dist-info/WHEEL
deptrace-0.1.0.dist-info/top_level.txt
deptrace-0.1.0.dist-info/RECORD
