Metadata-Version: 2.4
Name: deptrace
Version: 0.1.0
Summary: Analyze dependencies in a Python project
Requires-Python: >=3.13
